oslo_messaging/__init__.py
oslo_messaging/_utils.py
oslo_messaging/conffixture.py
oslo_messaging/dispatcher.py
oslo_messaging/exceptions.py
oslo_messaging/opts.py
oslo_messaging/serializer.py
oslo_messaging/server.py
oslo_messaging/target.py
oslo_messaging/transport.py
oslo_messaging/version.py
oslo_messaging/_drivers/__init__.py
oslo_messaging/_drivers/amqp.py
oslo_messaging/_drivers/amqpdriver.py
oslo_messaging/_drivers/base.py
oslo_messaging/_drivers/common.py
oslo_messaging/_drivers/impl_fake.py
oslo_messaging/_drivers/impl_kafka.py
oslo_messaging/_drivers/impl_rabbit.py
oslo_messaging/_drivers/pool.py
oslo_messaging/_drivers/kafka_driver/__init__.py
oslo_messaging/_drivers/kafka_driver/kafka_options.py
oslo_messaging/_metrics/__init__.py
oslo_messaging/_metrics/client.py
oslo_messaging/hacking/__init__.py
oslo_messaging/hacking/checks.py
oslo_messaging/notify/__init__.py
oslo_messaging/notify/_impl_log.py
oslo_messaging/notify/_impl_noop.py
oslo_messaging/notify/_impl_routing.py
oslo_messaging/notify/_impl_test.py
oslo_messaging/notify/dispatcher.py
oslo_messaging/notify/filter.py
oslo_messaging/notify/listener.py
oslo_messaging/notify/log_handler.py
oslo_messaging/notify/logger.py
oslo_messaging/notify/messaging.py
oslo_messaging/notify/middleware.py
oslo_messaging/notify/notifier.py
oslo_messaging/rpc/__init__.py
oslo_messaging/rpc/client.py
oslo_messaging/rpc/dispatcher.py
oslo_messaging/rpc/server.py
oslo_messaging/rpc/transport.py
oslo_messaging/tests/__init__.py
oslo_messaging/tests/test_config_opts_proxy.py
oslo_messaging/tests/test_exception_serialization.py
oslo_messaging/tests/test_expected_exceptions.py
oslo_messaging/tests/test_fixture.py
oslo_messaging/tests/test_opts.py
oslo_messaging/tests/test_target.py
oslo_messaging/tests/test_transport.py
oslo_messaging/tests/test_urls.py
oslo_messaging/tests/test_utils.py
oslo_messaging/tests/utils.py
oslo_messaging/tests/drivers/__init__.py
oslo_messaging/tests/drivers/test_impl_kafka.py
oslo_messaging-17.2.0.dist-info/licenses/AUTHORS
oslo_messaging-17.2.0.dist-info/licenses/LICENSE
oslo_messaging-17.2.0.dist-info/METADATA
oslo_messaging-17.2.0.dist-info/WHEEL
oslo_messaging-17.2.0.dist-info/entry_points.txt
oslo_messaging-17.2.0.dist-info/pbr.json
oslo_messaging-17.2.0.dist-info/top_level.txt
oslo_messaging-17.2.0.dist-info/RECORD
